outcome/logkit/__init__.py
outcome/logkit/context.py
outcome/logkit/features.py
outcome/logkit/filters.py
outcome/logkit/fixtures/__init__.py
outcome/logkit/fixtures/log_output.py
outcome/logkit/init.py
outcome/logkit/intercept.py
outcome/logkit/logger.py
outcome/logkit/proxy.py
outcome/logkit/py.typed
outcome/logkit/stackdriver.py
outcome/logkit/types.py
outcome_logkit-1.2.0.dist-info/WHEEL
outcome_logkit-1.2.0.dist-info/METADATA
outcome_logkit-1.2.0.dist-info/RECORD
