Metadata-Version: 2.1
Name: outcome-logkit
Version: 1.2.0
Summary: Logging helpers.
Home-page: https://github.com/outcome-co/logkit-py
Author: Outcome Engineering
Author-email: engineering@outcome.co
Requires-Python: >=3.8.6,<4.0.0
Classifier: Programming Language :: Python :: 3
Classifier: Programming Language :: Python :: 3.9
Requires-Dist: outcome-utils (>=5.0.3,<6.0.0)
Requires-Dist: structlog (>=20.1.0,<21.0.0)
Project-URL: Documentation, https://github.com/outcome-co/logkit-py#README
Project-URL: Repository, https://github.com/outcome-co/logkit-py
